httperactor/__about__.py
httperactor/__init__.py
httperactor/client.py
httperactor/error_handler.py
httperactor/http_method.py
httperactor/interactor.py
httperactor/py.typed
httperactor/abc/__init__.py
httperactor/abc/auth_middleware.py
httperactor/abc/client.py
httperactor/abc/error_handler.py
httperactor/abc/request.py
httperactor-0.1.1.dist-info/METADATA
httperactor-0.1.1.dist-info/WHEEL
httperactor-0.1.1.dist-info/licenses/LICENSE
httperactor-0.1.1.dist-info/RECORD
